MANIFEST.in
README.md
setup.py
csrc/warpat/cuda.h
csrc/warpat/cuda_error.h
csrc/warpat/warp_attention_api_torch.cpp
warp_attention/__init__.py
warp_attention/_version.py
warp_attention.egg-info/PKG-INFO
warp_attention.egg-info/SOURCES.txt
warp_attention.egg-info/dependency_links.txt
warp_attention.egg-info/top_level.txt
warp_attention/assets/kernel_config.pt
warp_attention/assets/map_to_best_version.pt
warp_attention/assets/warp_attn_forward_sm80.cubin
warp_attention/assets/warp_attn_forward_sm80_win.cubin
warp_attention/assets/warp_attn_forward_sm86.cubin
warp_attention/assets/warp_attn_forward_sm86_win.cubin
warp_attention/util/__init__.py
warp_attention/util/baseline_tester.py
warp_attention/util/benchmark.py
warp_attention/util/check_error.py
warp_attention/util/compare.py
warp_attention/util/tuning.py
warp_attention/util/util.py
warp_attention/util/warpat_tester.py